[
    {
        "cpu_id": 0,
        "sim_time": 30.008321329998115,
        "blue_alive": true,
        "red_alive": true,
        "Blue_ground": 0,
        "Red_ground": 0,
        "reward": 0.0,
        "f16_phi": -6.198059391491444,
        "f16_theta": 0.8853740799210813,
        "f16_psi": 344.3972793383111,
        "f16_lat": 58.38592031846887,
        "f16_long": 17.96362706607162,
        "f16_alt": 10364.359331585125,
        "f16_mach": 1.086092867980794,
        "sam1_alt": 10270.698114273531,
        "sam1_mach": 2.7688896225021216,
        "sam1_lat": 58.4261083152546,
        "sam1_long": 17.963153765522115,
        "sam1_psi": 150.55018228842778,
        "sam1_target_pos": 4564,
        "sam2_alt": 14545.682627695433,
        "sam2_mach": 2.8983560445961154,
        "sam2_lat": 59.31536650071338,
        "sam2_long": 17.630934308513464,
        "sam2_psi": 163.4268028930627,
        "sam2_target_pos": 105671,
        "f16r_phi": 0.3863979318019808,
        "f16r_theta": -12.82344670731308,
        "f16r_psi": 180.40160072885493,
        "f16r_lat": 58.90879635317543,
        "f16r_long": 17.999316072496043,
        "f16r_alt": 9932.66781343402,
        "f16r_mach": 1.107063602975597,
        "aim1_active": true,
        "aim1_alive": true,
        "aim1_target_lost": false,
        "aim1_target_hit": false,
        "aim2_active": false,
        "aim2_alive": true,
        "aim2_target_lost": false,
        "aim2_target_hit": false,
        "aim1r_active": true,
        "aim1r_alive": true,
        "aim1r_target_lost": false,
        "aim1r_target_hit": false
    },
    {
        "cpu_id": 0,
        "sim_time": 60.00830932999542,
        "blue_alive": true,
        "red_alive": true,
        "Blue_ground": 0,
        "Red_ground": 0,
        "reward": 0.0,
        "f16_phi": 8.773268562607639,
        "f16_theta": -21.506395361271743,
        "f16_psi": 345.9664977955087,
        "f16_lat": 58.46266853946176,
        "f16_long": 17.924099846731462,
        "f16_alt": 3962.8614917699665,
        "f16_mach": 1.3129263501137305,
        "sam1_alt": -2111.094491533336,
        "sam1_mach": 1.8429208931128667,
        "sam1_lat": 58.294846836455974,
        "sam1_long": 17.962097680796933,
        "sam1_psi": 84.96958435810316,
        "sam1_target_pos": 19763,
        "sam2_alt": 13969.659263479258,
        "sam2_mach": 2.4739102521459286,
        "sam2_lat": 59.11053267524323,
        "sam2_long": 17.74108027739558,
        "sam2_psi": 172.2957247018206,
        "sam2_target_pos": 73795,
        "f16r_phi": 1.4503362808851996,
        "f16r_theta": 2.743462936514646,
        "f16r_psi": 225.01216953611657,
        "f16r_lat": 58.833918646750924,
        "f16r_long": 17.938057900847035,
        "f16r_alt": 6906.122903411222,
        "f16r_mach": 1.0664472046489075,
        "aim1_active": true,
        "aim1_alive": true,
        "aim1_target_lost": false,
        "aim1_target_hit": false,
        "aim2_active": false,
        "aim2_alive": true,
        "aim2_target_lost": false,
        "aim2_target_hit": false,
        "aim1r_active": true,
        "aim1r_alive": true,
        "aim1r_target_lost": false,
        "aim1r_target_hit": false
    },
    {
        "cpu_id": 0,
        "sim_time": 90.00829732999273,
        "blue_alive": true,
        "red_alive": false,
        "Blue_ground": 0,
        "Red_ground": 0,
        "reward": 0.0,
        "f16_phi": 5.584557420707405,
        "f16_theta": -0.8031705761284599,
        "f16_psi": 8.761635941502293,
        "f16_lat": 58.56352696842001,
        "f16_long": 17.93539923670513,
        "f16_alt": 2345.0786359289737,
        "f16_mach": 1.052150207857232,
        "sam1_alt": -16208.341779044107,
        "sam1_mach": 0.8452868751246829,
        "sam1_lat": 58.30072279925239,
        "sam1_long": 17.953714483221443,
        "sam1_psi": 346.75903037640825,
        "sam1_target_pos": 34632,
        "sam2_alt": 13636.344371881074,
        "sam2_mach": 2.128669024603111,
        "sam2_lat": 58.93083800546946,
        "sam2_long": 17.802678269579218,
        "sam2_psi": 161.52142078124413,
        "sam2_target_pos": 43246,
        "f16r_phi": 80.12869754413505,
        "f16r_theta": 34.25390179938342,
        "f16r_psi": 237.20937050236282,
        "f16r_lat": 58.77322121788825,
        "f16r_long": 17.823419041790324,
        "f16r_alt": 7976.1200312749215,
        "f16r_mach": 0.8978038946378828,
        "aim1_active": false,
        "aim1_alive": false,
        "aim1_target_lost": false,
        "aim1_target_hit": true,
        "aim2_active": true,
        "aim2_alive": true,
        "aim2_target_lost": false,
        "aim2_target_hit": false,
        "aim1r_active": false,
        "aim1r_alive": false,
        "aim1r_target_lost": true,
        "aim1r_target_hit": false
    },
    {
        "cpu_id": 1,
        "sim_time": 30.008321329998115,
        "blue_alive": true,
        "red_alive": true,
        "Blue_ground": 0,
        "Red_ground": 0,
        "reward": 0.0,
        "f16_phi": 3.2979813463100878,
        "f16_theta": 0.6336866495799408,
        "f16_psi": 3.4760476339444057,
        "f16_lat": 58.389788774636315,
        "f16_long": 18.00619163819229,
        "f16_alt": 10168.158130473734,
        "f16_mach": 1.0990843090490685,
        "sam1_alt": 13755.524078754197,
        "sam1_mach": 3.123137874865108,
        "sam1_lat": 58.56763880154223,
        "sam1_long": 17.820641783883637,
        "sam1_psi": 129.14755368049168,
        "sam1_target_pos": 22955,
        "sam2_alt": 14536.63183606065,
        "sam2_mach": 2.8735808770521443,
        "sam2_lat": 59.25531872534266,
        "sam2_long": 17.46798923059284,
        "sam2_psi": 147.4142846268847,
        "sam2_target_pos": 101672,
        "f16r_phi": -0.0478485497267793,
        "f16r_theta": -12.833570854154274,
        "f16r_psi": 180.08101849700083,
        "f16r_lat": 58.90878652608415,
        "f16r_long": 17.999848165616726,
        "f16r_alt": 9932.331393140477,
        "f16r_mach": 1.1074476355833003,
        "aim1_active": true,
        "aim1_alive": true,
        "aim1_target_lost": false,
        "aim1_target_hit": false,
        "aim2_active": false,
        "aim2_alive": true,
        "aim2_target_lost": false,
        "aim2_target_hit": false,
        "aim1r_active": true,
        "aim1r_alive": true,
        "aim1r_target_lost": false,
        "aim1r_target_hit": false
    },
    {
        "cpu_id": 1,
        "sim_time": 60.00830932999542,
        "blue_alive": true,
        "red_alive": true,
        "Blue_ground": 0,
        "Red_ground": 0,
        "reward": 0.0,
        "f16_phi": 0.00856896171552669,
        "f16_theta": -34.333090467673934,
        "f16_psi": 3.4335796818073314,
        "f16_lat": 58.46814598835025,
        "f16_long": 18.015019917223427,
        "f16_alt": 3468.7769422509223,
        "f16_mach": 1.3323918035853863,
        "sam1_alt": 1127.4877560660482,
        "sam1_mach": 2.199467570052291,
        "sam1_lat": 58.43503226276831,
        "sam1_long": 18.025463938387205,
        "sam1_psi": 24.77044654612354,
        "sam1_target_pos": 4359,
        "sam2_alt": 13966.222988949405,
        "sam2_mach": 2.4568940888167483,
        "sam2_lat": 59.075369685039355,
        "sam2_long": 17.68214770309694,
        "sam2_psi": 155.60193816590836,
        "sam2_target_pos": 71272,
        "f16r_phi": -0.5550111543532043,
        "f16r_theta": 1.3660466804551465,
        "f16r_psi": 219.95982509429052,
        "f16r_lat": 58.83160346757427,
        "f16r_long": 17.942786772412276,
        "f16r_alt": 6951.4158611918365,
        "f16r_mach": 1.0811871042116357,
        "aim1_active": true,
        "aim1_alive": true,
        "aim1_target_lost": false,
        "aim1_target_hit": false,
        "aim2_active": false,
        "aim2_alive": true,
        "aim2_target_lost": false,
        "aim2_target_hit": false,
        "aim1r_active": true,
        "aim1r_alive": true,
        "aim1r_target_lost": false,
        "aim1r_target_hit": false
    },
    {
        "cpu_id": 1,
        "sim_time": 90.00829732999273,
        "blue_alive": true,
        "red_alive": false,
        "Blue_ground": 0,
        "Red_ground": 0,
        "reward": 0.0,
        "f16_phi": -4.002056437013056,
        "f16_theta": -0.6150506313250623,
        "f16_psi": 359.1146826239151,
        "f16_lat": 58.5702320877379,
        "f16_long": 18.01592759508116,
        "f16_alt": 3009.629714045191,
        "f16_mach": 1.0566885337662393,
        "sam1_alt": -14974.681115174792,
        "sam1_mach": 0.9232080151178084,
        "sam1_lat": 58.43554256873007,
        "sam1_long": 18.023453308285852,
        "sam1_psi": 64.19565531892619,
        "sam1_target_pos": 23388,
        "sam2_alt": 13621.648603788266,
        "sam2_mach": 2.116126329753222,
        "sam2_lat": 58.911287587763084,
        "sam2_long": 17.83205471857611,
        "sam2_psi": 156.02971733875458,
        "sam2_target_pos": 40966,
        "f16r_phi": 79.78432406801022,
        "f16r_theta": 34.29369352181182,
        "f16r_psi": 227.57792810655434,
        "f16r_lat": 58.76396425285744,
        "f16r_long": 17.840640498109238,
        "f16r_alt": 7979.943968590764,
        "f16r_mach": 0.9050039137061167,
        "aim1_active": false,
        "aim1_alive": false,
        "aim1_target_lost": false,
        "aim1_target_hit": true,
        "aim2_active": true,
        "aim2_alive": true,
        "aim2_target_lost": false,
        "aim2_target_hit": false,
        "aim1r_active": false,
        "aim1r_alive": false,
        "aim1r_target_lost": true,
        "aim1r_target_hit": false
    },
    {
        "cpu_id": 2,
        "sim_time": 30.008321329998115,
        "blue_alive": true,
        "red_alive": true,
        "Blue_ground": 0,
        "Red_ground": 0,
        "reward": 0.0,
        "f16_phi": -6.143991743042412,
        "f16_theta": 1.1202880210082593,
        "f16_psi": 336.8159691498228,
        "f16_lat": 58.38095410165132,
        "f16_long": 17.94747750568565,
        "f16_alt": 10583.730826591507,
        "f16_mach": 1.060532980885369,
        "sam1_alt": 14590.628650039227,
        "sam1_mach": 3.0843134798296576,
        "sam1_lat": 58.75807236260349,
        "sam1_long": 18.558671635550244,
        "sam1_psi": 262.6929102121716,
        "sam1_target_pos": 55349,
        "sam2_alt": 14570.166065943602,
        "sam2_mach": 2.9415425479795045,
        "sam2_lat": 59.416811364786966,
        "sam2_long": 18.204218137813836,
        "sam2_psi": 195.36044825003393,
        "sam2_target_pos": 116715,
        "f16r_phi": 1.0114534521744023,
        "f16r_theta": -7.998656394392895,
        "f16r_psi": 180.5541248174969,
        "f16r_lat": 58.908775938260554,
        "f16r_long": 17.999115140209245,
        "f16r_alt": 9965.433271558937,
        "f16r_mach": 1.1099453455570645,
        "aim1_active": true,
        "aim1_alive": true,
        "aim1_target_lost": false,
        "aim1_target_hit": false,
        "aim2_active": false,
        "aim2_alive": true,
        "aim2_target_lost": false,
        "aim2_target_hit": false,
        "aim1r_active": true,
        "aim1r_alive": true,
        "aim1r_target_lost": false,
        "aim1r_target_hit": false
    },
    {
        "cpu_id": 2,
        "sim_time": 60.00830932999542,
        "blue_alive": true,
        "red_alive": true,
        "Blue_ground": 0,
        "Red_ground": 0,
        "reward": 0.0,
        "f16_phi": 0.008321730007937617,
        "f16_theta": -30.644743726587382,
        "f16_psi": 337.4464559564266,
        "f16_lat": 58.45214532697097,
        "f16_long": 17.89051517861912,
        "f16_alt": 4095.9321473871055,
        "f16_mach": 1.328155462652564,
        "sam1_alt": 14019.97250037566,
        "sam1_mach": 2.601731550866915,
        "sam1_lat": 58.706008993284584,
        "sam1_long": 18.14440751078201,
        "sam1_psi": 222.97263818768926,
        "sam1_target_pos": 33518,
        "sam2_alt": 13980.797405118683,
        "sam2_mach": 2.5048263312477674,
        "sam2_lat": 59.209070833155,
        "sam2_long": 18.090859716921205,
        "sam2_psi": 197.1292590348527,
        "sam2_target_pos": 85870,
        "f16r_phi": 2.2007415120373333,
        "f16r_theta": 4.382488722110252,
        "f16r_psi": 227.0456818241772,
        "f16r_lat": 58.833956466364654,
        "f16r_long": 17.940492674096415,
        "f16r_alt": 6852.136613741425,
        "f16r_mach": 1.0633946101429703,
        "aim1_active": true,
        "aim1_alive": true,
        "aim1_target_lost": false,
        "aim1_target_hit": false,
        "aim2_active": false,
        "aim2_alive": true,
        "aim2_target_lost": false,
        "aim2_target_hit": false,
        "aim1r_active": true,
        "aim1r_alive": true,
        "aim1r_target_lost": false,
        "aim1r_target_hit": false
    },
    {
        "cpu_id": 2,
        "sim_time": 90.00829732999273,
        "blue_alive": true,
        "red_alive": false,
        "Blue_ground": 0,
        "Red_ground": 0,
        "reward": 0.6,
        "f16_phi": 5.882804941142281,
        "f16_theta": -0.653066584676423,
        "f16_psi": 349.0689925647502,
        "f16_lat": 58.552092180949366,
        "f16_long": 17.844491674617565,
        "f16_alt": 3422.504639039746,
        "f16_mach": 1.067071094639476,
        "sam1_alt": 7055.793116880951,
        "sam1_mach": 2.223529128580665,
        "sam1_lat": 58.58781572076115,
        "sam1_long": 17.88312687177001,
        "sam1_psi": 243.26150074165122,
        "sam1_target_pos": 5907,
        "sam2_alt": 13660.779924055518,
        "sam2_mach": 2.151611003501723,
        "sam2_lat": 59.03339828517592,
        "sam2_long": 17.980402045156016,
        "sam2_psi": 199.73212815663175,
        "sam2_target_pos": 55278,
        "f16r_phi": 84.33793442817452,
        "f16r_theta": 37.15658059439394,
        "f16r_psi": 249.904734221145,
        "f16r_lat": 58.77775213810825,
        "f16r_long": 17.820185192846637,
        "f16r_alt": 8012.573255972386,
        "f16r_mach": 0.882471481997485,
        "aim1_active": false,
        "aim1_alive": false,
        "aim1_target_lost": false,
        "aim1_target_hit": true,
        "aim2_active": true,
        "aim2_alive": true,
        "aim2_target_lost": false,
        "aim2_target_hit": false,
        "aim1r_active": false,
        "aim1r_alive": false,
        "aim1r_target_lost": true,
        "aim1r_target_hit": false
    },
    {
        "cpu_id": 3,
        "sim_time": 30.008321329998115,
        "blue_alive": true,
        "red_alive": true,
        "Blue_ground": 0,
        "Red_ground": 0,
        "reward": 0.0,
        "f16_phi": -0.47996408157781795,
        "f16_theta": 1.1313266343926414,
        "f16_psi": 359.73386933531117,
        "f16_lat": 58.38408257602016,
        "f16_long": 17.999476453191278,
        "f16_alt": 10791.055723234409,
        "f16_mach": 1.0511803722873936,
        "sam1_alt": 14630.73035060589,
        "sam1_mach": 3.0456848031745953,
        "sam1_lat": 58.6246990879447,
        "sam1_long": 18.506815374023812,
        "sam1_psi": 260.89905701682596,
        "sam1_target_pos": 40236,
        "sam2_alt": 14589.121671369223,
        "sam2_mach": 2.9986754883542095,
        "sam2_lat": 58.98706844095325,
        "sam2_long": 17.291649597786027,
        "sam2_psi": 121.88590333659288,
        "sam2_target_pos": 79038,
        "f16r_phi": -0.010636508428052192,
        "f16r_theta": -8.004425956463463,
        "f16r_psi": 180.1281376315698,
        "f16r_lat": 58.90876163537059,
        "f16r_long": 17.999778883571008,
        "f16r_alt": 9965.031670956365,
        "f16r_mach": 1.1104570187879053,
        "aim1_active": true,
        "aim1_alive": true,
        "aim1_target_lost": false,
        "aim1_target_hit": false,
        "aim2_active": false,
        "aim2_alive": true,
        "aim2_target_lost": false,
        "aim2_target_hit": false,
        "aim1r_active": true,
        "aim1r_alive": true,
        "aim1r_target_lost": false,
        "aim1r_target_hit": false
    },
    {
        "cpu_id": 3,
        "sim_time": 60.00830932999542,
        "blue_alive": true,
        "red_alive": true,
        "Blue_ground": 0,
        "Red_ground": 0,
        "reward": 0.0,
        "f16_phi": 0.009252791213955369,
        "f16_theta": -38.62792942725695,
        "f16_psi": 359.9667034771152,
        "f16_lat": 58.46023741922606,
        "f16_long": 17.999129842660057,
        "f16_alt": 4289.593572214553,
        "f16_mach": 1.3405306139339064,
        "sam1_alt": 9897.663277646006,
        "sam1_mach": 2.6246893909237525,
        "sam1_lat": 58.56122459411133,
        "sam1_long": 18.126983686016427,
        "sam1_psi": 216.9772334570159,
        "sam1_target_pos": 14703,
        "sam2_alt": 14001.840180848569,
        "sam2_mach": 2.544189455453523,
        "sam2_lat": 58.860712390555356,
        "sam2_long": 17.635782124525623,
        "sam2_psi": 145.15848305890822,
        "sam2_target_pos": 50429,
        "f16r_phi": 0.197308753587689,
        "f16r_theta": 1.985509579219836,
        "f16r_psi": 220.83739123158804,
        "f16r_lat": 58.83135890026115,
        "f16r_long": 17.945792867620447,
        "f16r_alt": 6931.144220294542,
        "f16r_mach": 1.0805349365226338,
        "aim1_active": true,
        "aim1_alive": true,
        "aim1_target_lost": false,
        "aim1_target_hit": false,
        "aim2_active": false,
        "aim2_alive": true,
        "aim2_target_lost": false,
        "aim2_target_hit": false,
        "aim1r_active": true,
        "aim1r_alive": true,
        "aim1r_target_lost": false,
        "aim1r_target_hit": false
    },
    {
        "cpu_id": 3,
        "sim_time": 90.00829732999273,
        "blue_alive": true,
        "red_alive": false,
        "Blue_ground": 0,
        "Red_ground": 0,
        "reward": 0.0,
        "f16_phi": 0.7627943367516897,
        "f16_theta": -0.8154066932838282,
        "f16_psi": 1.2775007322239504,
        "f16_lat": 58.56528420979113,
        "f16_long": 18.002187151463552,
        "f16_alt": 2520.9652674497993,
        "f16_mach": 1.0826383190732112,
        "sam1_alt": -5813.226405065024,
        "sam1_mach": 1.5469530880111637,
        "sam1_lat": 58.51157811089728,
        "sam1_long": 17.957700641197444,
        "sam1_psi": 236.0390363392903,
        "sam1_target_pos": 10533,
        "sam2_alt": 12749.405398205952,
        "sam2_mach": 2.2219153201560187,
        "sam2_lat": 58.71334499478349,
        "sam2_long": 17.856674603992396,
        "sam2_psi": 136.8165725624553,
        "sam2_target_pos": 21250,
        "f16r_phi": 66.66773847903467,
        "f16r_theta": 33.279692979971614,
        "f16r_psi": 222.5454868948293,
        "f16r_lat": 58.76432788126191,
        "f16r_long": 17.840827043232768,
        "f16r_alt": 7876.8585084546,
        "f16r_mach": 0.9167632304615577,
        "aim1_active": false,
        "aim1_alive": false,
        "aim1_target_lost": false,
        "aim1_target_hit": true,
        "aim2_active": true,
        "aim2_alive": true,
        "aim2_target_lost": false,
        "aim2_target_hit": false,
        "aim1r_active": false,
        "aim1r_alive": false,
        "aim1r_target_lost": true,
        "aim1r_target_hit": false
    },
    {
        "cpu_id": 4,
        "sim_time": 30.008321329998115,
        "blue_alive": true,
        "red_alive": true,
        "Blue_ground": 0,
        "Red_ground": 0,
        "reward": 0.0,
        "f16_phi": 4.108517919504385,
        "f16_theta": 0.7273886326146726,
        "f16_psi": 18.94488683026009,
        "f16_lat": 58.38558946583729,
        "f16_long": 18.002482176742213,
        "f16_alt": 8539.597268067304,
        "f16_mach": 1.071188751875583,
        "sam1_alt": 14522.641780283484,
        "sam1_mach": 2.872507224346645,
        "sam1_lat": 59.372955125613416,
        "sam1_long": 18.10758201393996,
        "sam1_psi": 184.70576374540246,
        "sam1_target_pos": 110597,
        "sam2_alt": -1526.4855094359934,
        "sam2_mach": 1.8511238117318876,
        "sam2_lat": 58.44388519560152,
        "sam2_long": 17.861853252030485,
        "sam2_psi": 251.66644453006418,
        "sam2_target_pos": 14512,
        "f16r_phi": -0.09034521934399921,
        "f16r_theta": 31.016993652442746,
        "f16r_psi": 81.29882371429187,
        "f16r_lat": 58.942376135006626,
        "f16r_long": 18.082277200056087,
        "f16r_alt": 6382.500677504567,
        "f16r_mach": 1.043113976192282,
        "aim1_active": true,
        "aim1_alive": true,
        "aim1_target_lost": false,
        "aim1_target_hit": false,
        "aim2_active": false,
        "aim2_alive": true,
        "aim2_target_lost": false,
        "aim2_target_hit": false,
        "aim1r_active": false,
        "aim1r_alive": true,
        "aim1r_target_lost": false,
        "aim1r_target_hit": false
    },
    {
        "cpu_id": 4,
        "sim_time": 60.00830932999542,
        "blue_alive": true,
        "red_alive": true,
        "Blue_ground": 0,
        "Red_ground": 0,
        "reward": 0.0,
        "f16_phi": -8.1847120658314,
        "f16_theta": 1.5692802211972208,
        "f16_psi": 341.07363067636396,
        "f16_lat": 58.46209419808159,
        "f16_long": 17.991202902069674,
        "f16_alt": 9516.69937220655,
        "f16_mach": 0.9754316286161643,
        "sam1_alt": 13959.65683820579,
        "sam1_mach": 2.4548124387736534,
        "sam1_lat": 59.16289768776961,
        "sam1_long": 18.071996008963577,
        "sam1_psi": 186.2231344079614,
        "sam1_target_pos": 78545,
        "sam2_alt": 7471.691314710224,
        "sam2_mach": 0.727156009915686,
        "sam2_lat": 58.40042102859632,
        "sam2_long": 17.824799927008332,
        "sam2_psi": 41.469254141651945,
        "sam2_target_pos": 12098,
        "f16r_phi": -96.35671454744569,
        "f16r_theta": 16.667795025813827,
        "f16r_psi": 86.6362711975175,
        "f16r_lat": 58.975215322296236,
        "f16r_long": 18.17237900078789,
        "f16r_alt": 9540.656953619386,
        "f16r_mach": 0.6143260880869421,
        "aim1_active": true,
        "aim1_alive": true,
        "aim1_target_lost": false,
        "aim1_target_hit": false,
        "aim2_active": false,
        "aim2_alive": true,
        "aim2_target_lost": false,
        "aim2_target_hit": false,
        "aim1r_active": false,
        "aim1r_alive": true,
        "aim1r_target_lost": false,
        "aim1r_target_hit": false
    },
    {
        "cpu_id": 4,
        "sim_time": 90.00829732999273,
        "blue_alive": true,
        "red_alive": true,
        "Blue_ground": 0,
        "Red_ground": 0,
        "reward": 0.0,
        "f16_phi": -90.05411972454772,
        "f16_theta": -8.44903143934401,
        "f16_psi": 298.24057560042434,
        "f16_lat": 58.5004121736763,
        "f16_long": 17.91209900916508,
        "f16_alt": 11418.382480612716,
        "f16_mach": 0.7368570842642962,
        "sam1_alt": 13617.471935188883,
        "sam1_mach": 2.114379984668449,
        "sam1_lat": 58.98364947658791,
        "sam1_long": 18.022584546488986,
        "sam1_psi": 198.10816080288146,
        "sam1_target_pos": 54420,
        "sam2_alt": 9557.624229291925,
        "sam2_mach": 0.3066670720541139,
        "sam2_lat": 58.38875910479648,
        "sam2_long": 17.8441359952547,
        "sam2_psi": 249.42776074223138,
        "sam2_target_pos": 13204,
        "f16r_phi": -1.6435638151392962,
        "f16r_theta": 2.0681026731246863,
        "f16r_psi": 20.45114153598224,
        "f16r_lat": 59.01024178479474,
        "f16r_long": 18.2437982459995,
        "f16r_alt": 7919.705473380179,
        "f16r_mach": 0.842385592303918,
        "aim1_active": true,
        "aim1_alive": true,
        "aim1_target_lost": false,
        "aim1_target_hit": false,
        "aim2_active": false,
        "aim2_alive": true,
        "aim2_target_lost": false,
        "aim2_target_hit": false,
        "aim1r_active": false,
        "aim1r_alive": true,
        "aim1r_target_lost": false,
        "aim1r_target_hit": false
    },
    {
        "cpu_id": 4,
        "sim_time": 120.00828532999003,
        "blue_alive": true,
        "red_alive": false,
        "Blue_ground": 0,
        "Red_ground": 0,
        "reward": 0.4,
        "f16_phi": -5.035652057170316,
        "f16_theta": -0.545139364771018,
        "f16_psi": 305.597191309132,
        "f16_lat": 58.544379882877344,
        "f16_long": 17.80879079324812,
        "f16_alt": 8294.927329042215,
        "f16_mach": 1.046748490137546,
        "sam1_alt": 13260.420895291561,
        "sam1_mach": 1.8530182773543027,
        "sam1_lat": 58.83489973832974,
        "sam1_long": 17.92560285431887,
        "sam1_psi": 215.39512568973268,
        "sam1_target_pos": 33541,
        "sam2_alt": 3047.8175286308083,
        "sam2_mach": 1.043277420488193,
        "sam2_lat": 58.38096100432871,
        "sam2_long": 17.859132986428552,
        "sam2_psi": 96.81134504788598,
        "sam2_target_pos": 19176,
        "f16r_phi": 63.885886880197425,
        "f16r_theta": 38.040889851163016,
        "f16r_psi": 39.237736482669874,
        "f16r_lat": 59.07397791222881,
        "f16r_long": 18.290910371300047,
        "f16r_alt": 9242.532184406591,
        "f16r_mach": 0.7470159473526501,
        "aim1_active": false,
        "aim1_alive": false,
        "aim1_target_lost": false,
        "aim1_target_hit": true,
        "aim2_active": false,
        "aim2_alive": true,
        "aim2_target_lost": false,
        "aim2_target_hit": false,
        "aim1r_active": false,
        "aim1r_alive": true,
        "aim1r_target_lost": false,
        "aim1r_target_hit": false
    },
    {
        "cpu_id": 5,
        "sim_time": 30.008321329998115,
        "blue_alive": true,
        "red_alive": true,
        "Blue_ground": 0,
        "Red_ground": 0,
        "reward": 0.0,
        "f16_phi": -2.4143762789987835,
        "f16_theta": 1.558520701756797,
        "f16_psi": 357.45710702116236,
        "f16_lat": 58.38011507092016,
        "f16_long": 17.995239279370324,
        "f16_alt": 11181.097295866593,
        "f16_mach": 1.0117767587270805,
        "sam1_alt": 14574.716170855863,
        "sam1_mach": 2.9230311083883955,
        "sam1_lat": 58.79263713201465,
        "sam1_long": 18.75172123282336,
        "sam1_psi": 257.9154999725344,
        "sam1_target_pos": 63899,
        "sam2_alt": 14601.19970776425,
        "sam2_mach": 3.099437524782894,
        "sam2_lat": 58.69524178319084,
        "sam2_long": 18.468932407294954,
        "sam2_psi": 252.59383504465197,
        "sam2_target_pos": 44923,
        "f16r_phi": 0.02965722101328744,
        "f16r_theta": -8.008273595879956,
        "f16r_psi": 180.17102044948595,
        "f16r_lat": 58.908762347397484,
        "f16r_long": 17.99972347302849,
        "f16r_alt": 9965.037000918093,
        "f16r_mach": 1.1104548072551126,
        "aim1_active": true,
        "aim1_alive": true,
        "aim1_target_lost": false,
        "aim1_target_hit": false,
        "aim2_active": false,
        "aim2_alive": true,
        "aim2_target_lost": false,
        "aim2_target_hit": false,
        "aim1r_active": true,
        "aim1r_alive": true,
        "aim1r_target_lost": false,
        "aim1r_target_hit": false
    },
    {
        "cpu_id": 5,
        "sim_time": 60.00830932999542,
        "blue_alive": true,
        "red_alive": true,
        "Blue_ground": 0,
        "Red_ground": 0,
        "reward": 0.0,
        "f16_phi": 0.010624486753568543,
        "f16_theta": -43.58489086596285,
        "f16_psi": 357.8287398535706,
        "f16_lat": 58.454420046265795,
        "f16_long": 17.98955361997232,
        "f16_alt": 4843.363988323635,
        "f16_mach": 1.3407014348235133,
        "sam1_alt": 13970.145243966124,
        "sam1_mach": 2.493097218555712,
        "sam1_lat": 58.73218752000722,
        "sam1_long": 18.359920038247747,
        "sam1_psi": 226.47949224774925,
        "sam1_target_pos": 38908,
        "sam2_alt": 11936.523891900195,
        "sam2_mach": 2.6729430569619708,
        "sam2_lat": 58.5979637508252,
        "sam2_long": 18.101527358665393,
        "sam2_psi": 199.02931299644015,
        "sam2_target_pos": 18767,
        "f16r_phi": 0.4266682292583108,
        "f16r_theta": 2.1566644768709384,
        "f16r_psi": 221.38881024021697,
        "f16r_lat": 58.831583183019035,
        "f16r_long": 17.94528644033994,
        "f16r_alt": 6925.5184165806595,
        "f16r_mach": 1.0790104265910332,
        "aim1_active": true,
        "aim1_alive": true,
        "aim1_target_lost": false,
        "aim1_target_hit": false,
        "aim2_active": false,
        "aim2_alive": true,
        "aim2_target_lost": false,
        "aim2_target_hit": false,
        "aim1r_active": true,
        "aim1r_alive": true,
        "aim1r_target_lost": false,
        "aim1r_target_hit": false
    },
    {
        "cpu_id": 5,
        "sim_time": 90.00829732999273,
        "blue_alive": true,
        "red_alive": false,
        "Blue_ground": 0,
        "Red_ground": 0,
        "reward": 0.0,
        "f16_phi": 1.2593415877588636,
        "f16_theta": -0.6949010417768342,
        "f16_psi": 0.1238418040292277,
        "f16_lat": 58.55881635393726,
        "f16_long": 17.98802897795746,
        "f16_alt": 3645.1799789401803,
        "f16_mach": 1.098766683492948,
        "sam1_alt": 9458.384050900278,
        "sam1_mach": 2.214674260308461,
        "sam1_lat": 58.623302723378586,
        "sam1_long": 18.08750604073064,
        "sam1_psi": 247.10261908517185,
        "sam1_target_pos": 10974,
        "sam2_alt": -3536.8925109052066,
        "sam2_mach": 1.7279705555259326,
        "sam2_lat": 58.51683404341734,
        "sam2_long": 17.945644107162686,
        "sam2_psi": 251.99664362380096,
        "sam2_target_pos": 8868,
        "f16r_phi": 75.15326843775343,
        "f16r_theta": 11.162557894162026,
        "f16r_psi": 227.37310488630902,
        "f16r_lat": 58.763958549782565,
        "f16r_long": 17.834105266836204,
        "f16r_alt": 7106.362905796892,
        "f16r_mach": 1.0026557706551014,
        "aim1_active": false,
        "aim1_alive": false,
        "aim1_target_lost": false,
        "aim1_target_hit": true,
        "aim2_active": true,
        "aim2_alive": true,
        "aim2_target_lost": false,
        "aim2_target_hit": false,
        "aim1r_active": false,
        "aim1r_alive": false,
        "aim1r_target_lost": true,
        "aim1r_target_hit": false
    },
    {
        "cpu_id": 6,
        "sim_time": 30.008321329998115,
        "blue_alive": true,
        "red_alive": true,
        "Blue_ground": 0,
        "Red_ground": 0,
        "reward": 0.0,
        "f16_phi": 1.0222316407990393,
        "f16_theta": 0.627118101194846,
        "f16_psi": 1.2551588161877545,
        "f16_lat": 58.390014466013405,
        "f16_long": 18.00224985787884,
        "f16_alt": 10142.584255844675,
        "f16_mach": 1.101319121258042,
        "sam1_alt": 14597.690077727151,
        "sam1_mach": 3.002162703019253,
        "sam1_lat": 59.41480253876763,
        "sam1_long": 17.737863020457365,
        "sam1_psi": 166.77074719536913,
        "sam1_target_pos": 115563,
        "sam2_alt": 14615.921908995608,
        "sam2_mach": 3.140207914740065,
        "sam2_lat": 58.64171769511362,
        "sam2_long": 17.517721373293934,
        "sam2_psi": 100.81707907303554,
        "sam2_target_pos": 40178,
        "f16r_phi": 0.5798561358657397,
        "f16r_theta": 17.156403110444685,
        "f16r_psi": 285.13988799887306,
        "f16r_lat": 58.94122605161505,
        "f16r_long": 17.922115519803967,
        "f16r_alt": 6182.694564367658,
        "f16r_mach": 1.0630696204497831,
        "aim1_active": true,
        "aim1_alive": true,
        "aim1_target_lost": false,
        "aim1_target_hit": false,
        "aim2_active": false,
        "aim2_alive": true,
        "aim2_target_lost": false,
        "aim2_target_hit": false,
        "aim1r_active": false,
        "aim1r_alive": true,
        "aim1r_target_lost": false,
        "aim1r_target_hit": false
    },
    {
        "cpu_id": 6,
        "sim_time": 60.00830932999542,
        "blue_alive": true,
        "red_alive": true,
        "Blue_ground": 0,
        "Red_ground": 0,
        "reward": 0.0,
        "f16_phi": -6.994543490675352,
        "f16_theta": 1.2415767747936053,
        "f16_psi": 339.0936777862259,
        "f16_lat": 58.47141838082394,
        "f16_long": 17.960671693039128,
        "f16_alt": 10617.946909515615,
        "f16_mach": 1.0571807793417904,
        "sam1_alt": 14002.5901092789,
        "sam1_mach": 2.547451401546703,
        "sam1_lat": 59.19968431164772,
        "sam1_long": 17.825099790854946,
        "sam1_psi": 175.45012907254815,
        "sam1_target_pos": 81802,
        "sam2_alt": 12224.0288248133,
        "sam2_mach": 2.6718856506532185,
        "sam2_lat": 58.55150100703729,
        "sam2_long": 17.88946969543606,
        "sam2_psi": 172.3204466837939,
        "sam2_target_pos": 10065,
        "f16r_phi": 167.88883431556516,
        "f16r_theta": 27.14059568637169,
        "f16r_psi": 283.4031131312832,
        "f16r_lat": 58.97209334068627,
        "f16r_long": 17.8365187963769,
        "f16r_alt": 9471.875780984357,
        "f16r_mach": 0.5915332436723073,
        "aim1_active": true,
        "aim1_alive": true,
        "aim1_target_lost": false,
        "aim1_target_hit": false,
        "aim2_active": false,
        "aim2_alive": true,
        "aim2_target_lost": false,
        "aim2_target_hit": false,
        "aim1r_active": false,
        "aim1r_alive": true,
        "aim1r_target_lost": false,
        "aim1r_target_hit": false
    },
    {
        "cpu_id": 6,
        "sim_time": 90.00829732999273,
        "blue_alive": true,
        "red_alive": true,
        "Blue_ground": 0,
        "Red_ground": 0,
        "reward": 0.0,
        "f16_phi": 1.1734829626581929,
        "f16_theta": 2.0393285957106198,
        "f16_psi": 340.80395814242365,
        "f16_lat": 58.54278017389446,
        "f16_long": 17.91158263977321,
        "f16_alt": 11662.141335983571,
        "f16_mach": 0.9717405509982835,
        "sam1_alt": 13699.441863673184,
        "sam1_mach": 2.183578396525087,
        "sam1_lat": 59.01272912892246,
        "sam1_long": 17.85003158575172,
        "sam1_psi": 182.20335958326135,
        "sam1_target_pos": 52677,
        "sam2_alt": 1331.918697565627,
        "sam2_mach": 2.02221303632615,
        "sam2_lat": 58.43148276344319,
        "sam2_long": 17.992160468234655,
        "sam2_psi": 312.70391224748226,
        "sam2_target_pos": 16792,
        "f16r_phi": -0.3805505212720943,
        "f16r_theta": 24.200551919555664,
        "f16r_psi": 351.2301447867855,
        "f16r_lat": 59.00068308376553,
        "f16r_long": 17.770501174117364,
        "f16r_alt": 7076.220109064082,
        "f16r_mach": 0.8192090719968101,
        "aim1_active": true,
        "aim1_alive": true,
        "aim1_target_lost": false,
        "aim1_target_hit": false,
        "aim2_active": false,
        "aim2_alive": true,
        "aim2_target_lost": false,
        "aim2_target_hit": false,
        "aim1r_active": false,
        "aim1r_alive": true,
        "aim1r_target_lost": false,
        "aim1r_target_hit": false
    },
    {
        "cpu_id": 6,
        "sim_time": 120.00828532999003,
        "blue_alive": true,
        "red_alive": false,
        "Blue_ground": 0,
        "Red_ground": 0,
        "reward": 0.0,
        "f16_phi": -5.259663861679397,
        "f16_theta": 1.1858513475942412,
        "f16_psi": 322.3744647999228,
        "f16_lat": 58.61194551601613,
        "f16_long": 17.83463603419227,
        "f16_alt": 10564.444191617973,
        "f16_mach": 1.0481596274071754,
        "sam1_alt": 13297.431536485023,
        "sam1_mach": 1.910209539219514,
        "sam1_lat": 58.851048177679104,
        "sam1_long": 17.832340826856242,
        "sam1_psi": 198.00418687819987,
        "sam1_target_pos": 26879,
        "sam2_alt": -3500.328167589453,
        "sam2_mach": 1.000730159493312,
        "sam2_lat": 58.52707621903975,
        "sam2_long": 17.86281595337265,
        "sam2_psi": 328.63952961064854,
        "sam2_target_pos": 17046,
        "f16r_phi": 2.520232859367189,
        "f16r_theta": 1.0482240869551354,
        "f16r_psi": 352.0456473467821,
        "f16r_lat": 59.06672608797718,
        "f16r_long": 17.751232478935773,
        "f16r_alt": 7954.556939850399,
        "f16r_mach": 0.8604705715953902,
        "aim1_active": false,
        "aim1_alive": false,
        "aim1_target_lost": false,
        "aim1_target_hit": true,
        "aim2_active": true,
        "aim2_alive": true,
        "aim2_target_lost": false,
        "aim2_target_hit": false,
        "aim1r_active": false,
        "aim1r_alive": true,
        "aim1r_target_lost": false,
        "aim1r_target_hit": false
    },
    {
        "cpu_id": 7,
        "sim_time": 30.008321329998115,
        "blue_alive": true,
        "red_alive": true,
        "Blue_ground": 0,
        "Red_ground": 0,
        "reward": 0.0,
        "f16_phi": -6.37377411716238,
        "f16_theta": 1.134248905752491,
        "f16_psi": 327.4892980740707,
        "f16_lat": 58.37700171061921,
        "f16_long": 17.930292619389576,
        "f16_alt": 10466.86030109321,
        "f16_mach": 1.0594461930208061,
        "sam1_alt": 10475.292083521932,
        "sam1_mach": 2.757932592419355,
        "sam1_lat": 58.37590107511233,
        "sam1_long": 17.925854244419636,
        "sam1_psi": 38.93822547873626,
        "sam1_target_pos": 307,
        "sam2_alt": 14599.984179583187,
        "sam2_mach": 3.0743087184917472,
        "sam2_lat": 59.0552598951697,
        "sam2_long": 18.8024947459851,
        "sam2_psi": 243.82818122701542,
        "sam2_target_pos": 91244,
        "f16r_phi": 2.903390180189631,
        "f16r_theta": 0.5228041643591756,
        "f16r_psi": 180.96348391453412,
        "f16r_lat": 58.908777328548844,
        "f16r_long": 17.99895203698835,
        "f16r_alt": 9972.867040151721,
        "f16r_mach": 1.1125578733858592,
        "aim1_active": false,
        "aim1_alive": true,
        "aim1_target_lost": false,
        "aim1_target_hit": false,
        "aim2_active": false,
        "aim2_alive": true,
        "aim2_target_lost": false,
        "aim2_target_hit": false,
        "aim1r_active": false,
        "aim1r_alive": true,
        "aim1r_target_lost": false,
        "aim1r_target_hit": false
    },
    {
        "cpu_id": 7,
        "sim_time": 60.00830932999542,
        "blue_alive": true,
        "red_alive": true,
        "Blue_ground": 0,
        "Red_ground": 0,
        "reward": 0.0,
        "f16_phi": 3.3052411111720814,
        "f16_theta": 1.5960801729223923,
        "f16_psi": 331.92930191659957,
        "f16_lat": 58.445282396850196,
        "f16_long": 17.856324796183667,
        "f16_alt": 11255.582777876232,
        "f16_mach": 1.0003017829806164,
        "sam1_alt": 3066.8307567440092,
        "sam1_mach": 2.025800451012078,
        "sam1_lat": 58.219203521963614,
        "sam1_long": 18.058453164460424,
        "sam1_psi": 106.72850799574626,
        "sam1_target_pos": 28993,
        "sam2_alt": 14021.005746116996,
        "sam2_mach": 2.5958883391615153,
        "sam2_lat": 58.95082490486947,
        "sam2_long": 18.417168569725362,
        "sam2_psi": 233.41887982756242,
        "sam2_target_pos": 65281,
        "f16r_phi": 2.656819166013356,
        "f16r_theta": 4.135104824560659,
        "f16r_psi": 228.40152986318287,
        "f16r_lat": 58.83574776574339,
        "f16r_long": 17.931413608025583,
        "f16r_alt": 7858.725578643859,
        "f16r_mach": 1.0362257076752925,
        "aim1_active": false,
        "aim1_alive": true,
        "aim1_target_lost": false,
        "aim1_target_hit": false,
        "aim2_active": false,
        "aim2_alive": true,
        "aim2_target_lost": false,
        "aim2_target_hit": false,
        "aim1r_active": true,
        "aim1r_alive": true,
        "aim1r_target_lost": false,
        "aim1r_target_hit": false
    },
    {
        "cpu_id": 7,
        "sim_time": 90.00829732999273,
        "blue_alive": false,
        "red_alive": true,
        "Blue_ground": 0,
        "Red_ground": 0,
        "reward": -1.0,
        "f16_phi": 0.009933230208047617,
        "f16_theta": -42.252098692750394,
        "f16_psi": 331.86205779490604,
        "f16_lat": 58.51036672322137,
        "f16_long": 17.7894612702346,
        "f16_alt": 4977.397913536862,
        "f16_mach": 1.338274038470925,
        "sam1_alt": -12841.820973791448,
        "sam1_mach": 1.0179172485196453,
        "sam1_lat": 58.1990626900807,
        "sam1_long": 18.05126691067231,
        "sam1_psi": 302.3604878539976,
        "sam1_target_pos": 41851,
        "sam2_alt": 13734.3385034989,
        "sam2_mach": 2.219586807920435,
        "sam2_lat": 58.834811239185825,
        "sam2_long": 18.124360182236618,
        "sam2_psi": 225.03856924058135,
        "sam2_target_pos": 42075,
        "f16r_phi": 84.80660566242132,
        "f16r_theta": 13.258055443332202,
        "f16r_psi": 249.54115984876734,
        "f16r_lat": 58.78133328854436,
        "f16r_long": 17.80519288294704,
        "f16r_alt": 8305.78286338816,
        "f16r_mach": 0.970777616094578,
        "aim1_active": true,
        "aim1_alive": true,
        "aim1_target_lost": false,
        "aim1_target_hit": false,
        "aim2_active": false,
        "aim2_alive": true,
        "aim2_target_lost": false,
        "aim2_target_hit": false,
        "aim1r_active": false,
        "aim1r_alive": false,
        "aim1r_target_lost": false,
        "aim1r_target_hit": true
    },
    {
        "cpu_id": 8,
        "sim_time": 30.008321329998115,
        "blue_alive": true,
        "red_alive": true,
        "Blue_ground": 0,
        "Red_ground": 0,
        "reward": 0.0,
        "f16_phi": -6.275222759115993,
        "f16_theta": 1.3027624189709694,
        "f16_psi": 349.9434883040479,
        "f16_lat": 58.38261505007768,
        "f16_long": 17.978779735990052,
        "f16_alt": 10859.279272619391,
        "f16_mach": 1.0448445469554033,
        "sam1_alt": 10634.381024172477,
        "sam1_mach": 2.8460986529624757,
        "sam1_lat": 58.47780898882782,
        "sam1_long": 17.93448796188665,
        "sam1_psi": 181.6969087291683,
        "sam1_target_pos": 11015,
        "sam2_alt": 13660.6002378588,
        "sam2_mach": 3.1259748559786154,
        "sam2_lat": 58.554020723208495,
        "sam2_long": 17.81851990736379,
        "sam2_psi": 146.1383454734437,
        "sam2_target_pos": 21549,
        "f16r_phi": -1.8723166447389812,
        "f16r_theta": 9.043595151588669,
        "f16r_psi": 75.25946379814683,
        "f16r_lat": 58.937378022960814,
        "f16r_long": 18.075705086696697,
        "f16r_alt": 6062.895448041514,
        "f16r_mach": 1.104112367061527,
        "aim1_active": true,
        "aim1_alive": true,
        "aim1_target_lost": false,
        "aim1_target_hit": false,
        "aim2_active": false,
        "aim2_alive": true,
        "aim2_target_lost": false,
        "aim2_target_hit": false,
        "aim1r_active": false,
        "aim1r_alive": true,
        "aim1r_target_lost": false,
        "aim1r_target_hit": false
    },
    {
        "cpu_id": 8,
        "sim_time": 60.00830932999542,
        "blue_alive": false,
        "red_alive": true,
        "Blue_ground": 0,
        "Red_ground": 0,
        "reward": -1.0,
        "f16_phi": -5.96251994018315,
        "f16_theta": 7.07824354581932,
        "f16_psi": 293.3798665368074,
        "f16_lat": 58.43768911810719,
        "f16_long": 17.872574019670907,
        "f16_alt": 10261.081941234434,
        "f16_mach": 1.0110039858888793,
        "sam1_alt": 13416.456573859818,
        "sam1_mach": 2.0795325119052586,
        "sam1_lat": 58.289064223725894,
        "sam1_long": 17.95261996013599,
        "sam1_psi": 306.6438421657731,
        "sam1_target_pos": 17466,
        "sam2_alt": 6103.4093967178615,
        "sam2_mach": 2.400783877882223,
        "sam2_lat": 58.372409521943,
        "sam2_long": 17.884148641534775,
        "sam2_psi": 137.25127716828965,
        "sam2_target_pos": 8339,
        "f16r_phi": -3.648096776657735,
        "f16r_theta": 4.061908975078865,
        "f16r_psi": 18.35925110570188,
        "f16r_lat": 59.000965309315994,
        "f16r_long": 18.155660893944816,
        "f16r_alt": 7854.687607183573,
        "f16r_mach": 0.9097307339779611,
        "aim1_active": true,
        "aim1_alive": true,
        "aim1_target_lost": false,
        "aim1_target_hit": false,
        "aim2_active": false,
        "aim2_alive": true,
        "aim2_target_lost": false,
        "aim2_target_hit": false,
        "aim1r_active": false,
        "aim1r_alive": true,
        "aim1r_target_lost": false,
        "aim1r_target_hit": false
    },
    {
        "cpu_id": 9,
        "sim_time": 30.008321329998115,
        "blue_alive": true,
        "red_alive": true,
        "Blue_ground": 0,
        "Red_ground": 0,
        "reward": 0.0,
        "f16_phi": -5.878106267882314,
        "f16_theta": 1.039104899734355,
        "f16_psi": 338.71336801465264,
        "f16_lat": 58.382215862789835,
        "f16_long": 17.95106099719838,
        "f16_alt": 10514.285316263813,
        "f16_mach": 1.067467537712569,
        "sam1_alt": 14633.123466974832,
        "sam1_mach": 3.082885160263334,
        "sam1_lat": 58.78692559976941,
        "sam1_long": 17.382182345172023,
        "sam1_psi": 119.44100163083607,
        "sam1_target_pos": 56251,
        "sam2_alt": 14573.0467542005,
        "sam2_mach": 2.9668750697194426,
        "sam2_lat": 59.22597923197432,
        "sam2_long": 17.34531280961184,
        "sam2_psi": 147.394704603007,
        "sam2_target_pos": 100659,
        "f16r_phi": 0.9336912538581039,
        "f16r_theta": -7.999873388357327,
        "f16r_psi": 180.52965167089948,
        "f16r_lat": 58.90877484028662,
        "f16r_long": 17.999153859470585,
        "f16r_alt": 9965.405012406529,
        "f16r_mach": 1.1099871563889225,
        "aim1_active": true,
        "aim1_alive": true,
        "aim1_target_lost": false,
        "aim1_target_hit": false,
        "aim2_active": false,
        "aim2_alive": true,
        "aim2_target_lost": false,
        "aim2_target_hit": false,
        "aim1r_active": true,
        "aim1r_alive": true,
        "aim1r_target_lost": false,
        "aim1r_target_hit": false
    },
    {
        "cpu_id": 9,
        "sim_time": 60.00830932999542,
        "blue_alive": true,
        "red_alive": true,
        "Blue_ground": 0,
        "Red_ground": 0,
        "reward": 0.0,
        "f16_phi": 0.008445524703186906,
        "f16_theta": -25.65831918901058,
        "f16_psi": 339.3311978057483,
        "f16_lat": 58.45515818623576,
        "f16_long": 17.898025285838873,
        "f16_alt": 4085.7239170930807,
        "f16_mach": 1.3195947973798083,
        "sam1_alt": 13877.94530785609,
        "sam1_mach": 2.609851123534459,
        "sam1_lat": 58.655543318601886,
        "sam1_long": 17.718776916032102,
        "sam1_psi": 162.6357498733645,
        "sam1_target_pos": 26621,
        "sam2_alt": 13990.076281055475,
        "sam2_mach": 2.521614114277784,
        "sam2_lat": 59.03931901903167,
        "sam2_long": 17.559787213378733,
        "sam2_psi": 162.34234895937317,
        "sam2_target_pos": 68839,
        "f16r_phi": 2.0970302794016336,
        "f16r_theta": 4.198473670744797,
        "f16r_psi": 226.618591238819,
        "f16r_lat": 58.83377992092349,
        "f16r_long": 17.9408278382624,
        "f16r_alt": 6858.227116678477,
        "f16r_mach": 1.064384296580054,
        "aim1_active": true,
        "aim1_alive": true,
        "aim1_target_lost": false,
        "aim1_target_hit": false,
        "aim2_active": false,
        "aim2_alive": true,
        "aim2_target_lost": false,
        "aim2_target_hit": false,
        "aim1r_active": true,
        "aim1r_alive": true,
        "aim1r_target_lost": false,
        "aim1r_target_hit": false
    },
    {
        "cpu_id": 9,
        "sim_time": 90.00829732999273,
        "blue_alive": false,
        "red_alive": true,
        "Blue_ground": 0,
        "Red_ground": 0,
        "reward": -1.0,
        "f16_phi": 5.160280097125714,
        "f16_theta": -0.7320771063462808,
        "f16_psi": 359.83480450648136,
        "f16_lat": 58.558517592205156,
        "f16_long": 17.886482105433334,
        "f16_alt": 2951.78243300997,
        "f16_mach": 1.0692701220259344,
        "sam1_alt": 1260.1062704348624,
        "sam1_mach": 2.0190682450216952,
        "sam1_lat": 58.55020285368009,
        "sam1_long": 17.902388079046514,
        "sam1_psi": 175.28308579346125,
        "sam1_target_pos": 2074,
        "sam2_alt": 13680.219188571955,
        "sam2_mach": 2.1642959018077144,
        "sam2_lat": 58.86549276865091,
        "sam2_long": 17.686660405171498,
        "sam2_psi": 152.92088206803038,
        "sam2_target_pos": 37769,
        "f16r_phi": 42.19072771384435,
        "f16r_theta": 34.32360297657365,
        "f16r_psi": 228.80078062632646,
        "f16r_lat": 58.774283984766214,
        "f16r_long": 17.821359601591105,
        "f16r_alt": 7744.490749821452,
        "f16r_mach": 0.9277372729140407,
        "aim1_active": false,
        "aim1_alive": false,
        "aim1_target_lost": false,
        "aim1_target_hit": true,
        "aim2_active": true,
        "aim2_alive": true,
        "aim2_target_lost": false,
        "aim2_target_hit": false,
        "aim1r_active": false,
        "aim1r_alive": false,
        "aim1r_target_lost": true,
        "aim1r_target_hit": false
    }
]